wabc/__init__.py
wabc/bot.py
wabc/context.py
wabc/classes/__init__.py
wabc/classes/enums.py
wabc/classes/events.py
wabc/classes/messages.py
wabc/classes/responses.py
wabc/core/__init__.py
wabc/core/client.py
wabc/core/converter.py
wabc/core/errors.py
wabc/core/http.py
wabc/utils/__init__.py
wabc/utils/ttl_dict.py
wabc-0.2.0.dist-info/AUTHORS.rst
wabc-0.2.0.dist-info/LICENSE
wabc-0.2.0.dist-info/METADATA
wabc-0.2.0.dist-info/WHEEL
wabc-0.2.0.dist-info/top_level.txt
wabc-0.2.0.dist-info/RECORD
