Metadata-Version: 2.1
Name: wabc
Version: 0.2.0
Summary: A modern, easy to use, feature-rich ready API wrapper for WhatsApp Business Cloud written in Python
Home-page: https://github.com/leandcesar/wabc
Author: Leandro César Cassimiro
Author-email: ccleandroc@gmail.com
License: MIT license
Keywords: whatsapp
Platform: UNKNOWN
Classifier: Development Status :: 2 - Pre-Alpha
Classifier: Intended Audience :: Developers
Classifier: License :: OSI Approved :: MIT License
Classifier: Programming Language :: Python :: 3
Classifier: Programming Language :: Python :: 3.6
Classifier: Programming Language :: Python :: 3.7
Classifier: Programming Language :: Python :: 3.8
Requires-Python: >=3.6
License-File: LICENSE
License-File: AUTHORS.rst
Requires-Dist: dacite (==1.6.0)
Requires-Dist: requests (==2.28.1)
